MANIFEST.in
README.md
requirements.txt
setup.cfg
setup.py
be150/__init__.py
be150/viz.py
be150.egg-info/PKG-INFO
be150.egg-info/SOURCES.txt
be150.egg-info/dependency_links.txt
be150.egg-info/top_level.txt