Metadata-Version: 1.1
Name: be150
Version: 0.0.3
Summary: Python utilities for the Caltech course BE 150: Design Principles of Genetic Circuits
Home-page: https://github.com/justinbois/be150
Author: Justin Bois
Author-email: bois@caltech.edu
License: BSD
Download-URL: https://github.com/justinbois/be150/tarball/0.0.3
Platform: UNKNOWN
Classifier: Development Status :: 3 - Alpha
Classifier: Intended Audience :: Developers
Classifier: Programming Language :: Python :: 3
